odoo/addons/website_sale_stock_available/README.rst
odoo/addons/website_sale_stock_available/__init__.py
odoo/addons/website_sale_stock_available/__manifest__.py
odoo/addons/website_sale_stock_available/controllers/__init__.py
odoo/addons/website_sale_stock_available/controllers/main.py
odoo/addons/website_sale_stock_available/i18n/ca.po
odoo/addons/website_sale_stock_available/i18n/es.po
odoo/addons/website_sale_stock_available/i18n/es_CL.po
odoo/addons/website_sale_stock_available/i18n/fr.po
odoo/addons/website_sale_stock_available/i18n/nl.po
odoo/addons/website_sale_stock_available/i18n/website_sale_stock_available.pot
odoo/addons/website_sale_stock_available/models/__init__.py
odoo/addons/website_sale_stock_available/models/product_product.py
odoo/addons/website_sale_stock_available/models/product_template.py
odoo/addons/website_sale_stock_available/models/sale_order.py
odoo/addons/website_sale_stock_available/readme/CONFIGURE.rst
odoo/addons/website_sale_stock_available/readme/CONTRIBUTORS.rst
odoo/addons/website_sale_stock_available/readme/DESCRIPTION.rst
odoo/addons/website_sale_stock_available/readme/USAGE.rst
odoo/addons/website_sale_stock_available/static/description/availability_message.png
odoo/addons/website_sale_stock_available/static/description/icon.png
odoo/addons/website_sale_stock_available/static/description/index.html
odoo/addons/website_sale_stock_available/static/description/product_quantities.png
odoo/addons/website_sale_stock_available/tests/__init__.py
odoo/addons/website_sale_stock_available/tests/test_website_sale_stock_available.py
odoo13_addon_website_sale_stock_available-13.0.1.0.1.dev8.dist-info/METADATA
odoo13_addon_website_sale_stock_available-13.0.1.0.1.dev8.dist-info/WHEEL
odoo13_addon_website_sale_stock_available-13.0.1.0.1.dev8.dist-info/top_level.txt
odoo13_addon_website_sale_stock_available-13.0.1.0.1.dev8.dist-info/RECORD
